{
    "D": {
        "France": [
            {
                "000005": {
                    "ADDRESS_1": "Margaret Oneal",
                    "CITY": "Edremit",
                    "CLIENT_ID": "EBD14318-D666-6375-76C7-D8AB807611E4",
                    "COUNTRY": "France",
                    "GROUP": "D",
                    "SEQUENCE_ID": "000005",
                    "STREET": "862-3081 Donec Street",
                    "ZIP": "758185"
                }
            },
            {
                "000009": {
                    "ADDRESS_1": "Chaney Pierce",
                    "CITY": "Inner Mongolia",
                    "CLIENT_ID": "6E88192D-D5C2-7EC1-CA4A-88449E56CD70",
                    "COUNTRY": "France",
                    "GROUP": "D",
                    "SEQUENCE_ID": "000009",
                    "STREET": "Ap #161-7851 Nisi. Rd.",
                    "ZIP": "188773"
                }
            },
            {
                "000013": {
                    "ADDRESS_1": "Eaton Cline",
                    "CITY": "San Isidro",
                    "CLIENT_ID": "876B040D-5ED5-3F74-C2B1-BC56D0EA56C7",
                    "COUNTRY": "France",
                    "GROUP": "D",
                    "SEQUENCE_ID": "000013",
                    "STREET": "429 Libero. Rd.",
                    "ZIP": "715841"
                }
            },
            {
                "000019": {
                    "ADDRESS_1": "Basil Stewart",
                    "CITY": "Emmen",
                    "CLIENT_ID": "DE1C3274-16A9-A9E9-55B1-CAA7C3A9BC98",
                    "COUNTRY": "France",
                    "GROUP": "D",
                    "SEQUENCE_ID": "000019",
                    "STREET": "Ap #120-5307 Vel Road",
                    "ZIP": "303071"
                }
            },
            {
                "000027": {
                    "ADDRESS_1": "Dale Justice",
                    "CITY": "Yogyakarta",
                    "CLIENT_ID": "2C892F8E-8B5E-4EDD-2E4D-1DB4B5D5D983",
                    "COUNTRY": "France",
                    "GROUP": "D",
                    "SEQUENCE_ID": "000027",
                    "STREET": "673-6448 Non Road",
                    "ZIP": "45444"
                }
            },
            {
                "000041": {
                    "ADDRESS_1": "Sage Wilcox",
                    "CITY": "Gmunden",
                    "CLIENT_ID": "D736C7B2-8936-F63B-E9EE-2B5936BDE595",
                    "COUNTRY": "France",
                    "GROUP": "D",
                    "SEQUENCE_ID": "000041",
                    "STREET": "110-3974 Mauris Road",
                    "ZIP": "3395"
                }
            },
            {
                "000049": {
                    "ADDRESS_1": "Fulton Gallagher",
                    "CITY": "Saint Paul",
                    "CLIENT_ID": "E8011CB7-B2F4-D0D4-1081-DE16BED2BC23",
                    "COUNTRY": "France",
                    "GROUP": "D",
                    "SEQUENCE_ID": "000049",
                    "STREET": "Ap #912-9209 Varius. Av.",
                    "ZIP": "51708"
                }
            },
            {
                "000055": {
                    "ADDRESS_1": "Colt Roberts",
                    "CITY": "Valbrevenna",
                    "CLIENT_ID": "1A4E7293-B75E-E9D4-89E3-F469F4A9642E",
                    "COUNTRY": "France",
                    "GROUP": "D",
                    "SEQUENCE_ID": "000055",
                    "STREET": "Ap #363-1542 Mauris St.",
                    "ZIP": "37772"
                }
            },
            {
                "000071": {
                    "ADDRESS_1": "Ginger Sampson",
                    "CITY": "Temuka",
                    "CLIENT_ID": "3A5AC694-1348-BA8A-23A9-6B1588566A93",
                    "COUNTRY": "France",
                    "GROUP": "D",
                    "SEQUENCE_ID": "000071",
                    "STREET": "937-8869 Vel Street",
                    "ZIP": "63483"
                }
            },
            {
                "000074": {
                    "ADDRESS_1": "Aristotle Duke",
                    "CITY": "Lauterach",
                    "CLIENT_ID": "0A7208B2-7045-8681-5758-1782C8E6CC9D",
                    "COUNTRY": "France",
                    "GROUP": "D",
                    "SEQUENCE_ID": "000074",
                    "STREET": "8164 Ipsum Street",
                    "ZIP": "22213"
                }
            },
            {
                "000088": {
                    "ADDRESS_1": "Henry Whitney",
                    "CITY": "Edmundston",
                    "CLIENT_ID": "C4583395-9DBF-694B-2DA5-21C3D85A4253",
                    "COUNTRY": "France",
                    "GROUP": "D",
                    "SEQUENCE_ID": "000088",
                    "STREET": "Ap #955-1555 Eget Street",
                    "ZIP": "32648"
                }
            },
            {
                "000096": {
                    "ADDRESS_1": "Thomas Dickerson",
                    "CITY": "La Thuile",
                    "CLIENT_ID": "2919DF16-5578-8AAE-4B26-6989195ADBF8",
                    "COUNTRY": "France",
                    "GROUP": "D",
                    "SEQUENCE_ID": "000096",
                    "STREET": "Ap #521-8673 Vitae Avenue",
                    "ZIP": "4639"
                }
            },
            {
                "000105": {
                    "ADDRESS_1": "Alice Villarreal",
                    "CITY": "Bajaur Agency",
                    "CLIENT_ID": "4D4916AB-70D4-453E-5336-712FD5764946",
                    "COUNTRY": "France",
                    "GROUP": "D",
                    "SEQUENCE_ID": "000105",
                    "STREET": "Ap #995-7631 Tempor Rd.",
                    "ZIP": "614761"
                }
            },
            {
                "000125": {
                    "ADDRESS_1": "Zeph Holcomb",
                    "CITY": "Tampa",
                    "CLIENT_ID": "9565783C-5958-A5AA-EA2A-AF5833A9BF92",
                    "COUNTRY": "France",
                    "GROUP": "D",
                    "SEQUENCE_ID": "000125",
                    "STREET": "812-8629 Dapibus Rd.",
                    "ZIP": "24283"
                }
            },
            {
                "000154": {
                    "ADDRESS_1": "Elaine Bradford",
                    "CITY": "Roubaix",
                    "CLIENT_ID": "135795C6-313B-47B9-2577-36A532347472",
                    "COUNTRY": "France",
                    "GROUP": "D",
                    "SEQUENCE_ID": "000154",
                    "STREET": "Ap #140-2667 In St.",
                    "ZIP": "U3O 2PH"
                }
            },
            {
                "000177": {
                    "ADDRESS_1": "Scarlett Best",
                    "CITY": "Breda",
                    "CLIENT_ID": "C80AED77-56FA-8D9D-B48C-ADCE08D4C7D5",
                    "COUNTRY": "France",
                    "GROUP": "D",
                    "SEQUENCE_ID": "000177",
                    "STREET": "142-3426 Dui. Street",
                    "ZIP": "814865"
                }
            },
            {
                "000181": {
                    "ADDRESS_1": "Nora Fry",
                    "CITY": "Olinda",
                    "CLIENT_ID": "73CBBBD7-1198-DC5C-71DE-B6974115C4C0",
                    "COUNTRY": "France",
                    "GROUP": "D",
                    "SEQUENCE_ID": "000181",
                    "STREET": "378-3619 Lectus. Avenue",
                    "ZIP": "18281"
                }
            }
        ]
    }
}